{
    "techcrunch.com": {
        "Time": 9.68,
        "URL": "techcrunch.com",
        "Resolver Status": "OK",
        "Resolver IP": "31.130.200.2",
        "DNS Status": "OK",
        "DNS IPs": [
            "212.82.100.163"
        ],
        "TCP Status": "Established",
        "TCP Remote IP": "212.82.100.163",
        "PING Status": "OK",
        "PING IP": "212.82.100.163",
        "Trace hop IP": "N/A",
        "Redirected Status": "Redirected",
        "Redirected Location": "https://techcrunch.com/",
        "Redirected Location IPs": [
            "OK",
            [
                "212.82.100.163"
            ]
        ],
        "HTTP Status": 200,
        "Content Length": 2798643,
        "Headers": {
            "Server": "ATS",
            "Date": "Sun, 28 Apr 2024 21:25:25 GMT",
            "Content-Type": "text/html; charset=UTF-8",
            "Vary": "Accept-Encoding",
            "X-hacker": "If you're reading this, you should visit wpvip.com/careers and apply to join the fun, mention this header.",
            "X-Powered-By": "WordPress VIP <https://wpvip.com>",
            "Host-Header": "a9130478a60e5f9135f765b23f26593b",
            "Content-Security-Policy": "default-src https: 'unsafe-inline' 'unsafe-eval' blob:; img-src * data: https:; object-src 'none'; connect-src https: wss:; script-src 'unsafe-inline' https: 'unsafe-eval'; worker-src 'self' blob:; upgrade-insecure-requests; block-all-mixed-content; sandbox allow-forms allow-same-origin allow-scripts allow-popups allow-popups-to-escape-sandbox; media-src 'self' blob: data: https:; font-src 'self' data: https://jac.yahoosandbox.com https://use.typekit.net https://cdn.vidible.tv https://cdnjs.cloudflare.com https://fonts.gstatic.com https://s0.wp.com ;",
            "Referrer-Policy": "no-referrer-when-downgrade",
            "Link": "<https://techcrunch.com/wp-json/>; rel=\"https://api.w.org/\"",
            "Content-Encoding": "gzip",
            "Strict-Transport-Security": "max-age=31536000",
            "x-rq": "lhr3 111 253 443",
            "accept-ranges": "bytes",
            "cache-control": "max-age=300, must-revalidate",
            "x-cache": "HIT",
            "Age": "0",
            "Transfer-Encoding": "chunked",
            "Connection": "keep-alive",
            "X-Content-Type-Options": "nosniff",
            "X-XSS-Protection": "1; mode=block",
            "X-Frame-Options": "SAMEORIGIN"
        },
        "HTML Content": "techcrunch.com_content.html",
        "Cert Status": "OK",
        "Cert Content": {
            "subject": [
                [
                    [
                        "countryName",
                        "US"
                    ]
                ],
                [
                    [
                        "stateOrProvinceName",
                        "New York"
                    ]
                ],
                [
                    [
                        "localityName",
                        "New York"
                    ]
                ],
                [
                    [
                        "organizationName",
                        "Yahoo Holdings Inc."
                    ]
                ],
                [
                    [
                        "commonName",
                        "www.makers.com"
                    ]
                ]
            ],
            "issuer": [
                [
                    [
                        "countryName",
                        "US"
                    ]
                ],
                [
                    [
                        "organizationName",
                        "DigiCert Inc"
                    ]
                ],
                [
                    [
                        "organizationalUnitName",
                        "www.digicert.com"
                    ]
                ],
                [
                    [
                        "commonName",
                        "DigiCert SHA2 High Assurance Server CA"
                    ]
                ]
            ],
            "version": 3,
            "serialNumber": "01B451E7EDC65F2DEAE0014868406439",
            "notBefore": "Mar 21 00:00:00 2024 GMT",
            "notAfter": "Sep 11 23:59:59 2024 GMT",
            "subjectAltName": [
                [
                    "DNS",
                    "www.makers.com"
                ],
                [
                    "DNS",
                    "www.intheknow.com"
                ],
                [
                    "DNS",
                    "www.builtbygirls.com"
                ],
                [
                    "DNS",
                    "www.aol.jp"
                ],
                [
                    "DNS",
                    "www.aol.de"
                ],
                [
                    "DNS",
                    "www.aol.co.uk"
                ],
                [
                    "DNS",
                    "www.aol.ca"
                ],
                [
                    "DNS",
                    "welcomescreen.aol.de"
                ],
                [
                    "DNS",
                    "wave.builtbygirls.com"
                ],
                [
                    "DNS",
                    "wave-stage.builtbygirls.com"
                ],
                [
                    "DNS",
                    "w.sb.welcomescreen.aol.com"
                ],
                [
                    "DNS",
                    "w.main.welcomescreen.aol.com"
                ],
                [
                    "DNS",
                    "venta.automoviles.aol.com"
                ],
                [
                    "DNS",
                    "toshiba.aol.ca"
                ],
                [
                    "DNS",
                    "techcrunch.com"
                ],
                [
                    "DNS",
                    "talktalk.aol.co.uk"
                ],
                [
                    "DNS",
                    "support.builtbygirls.com"
                ],
                [
                    "DNS",
                    "strictlyvc.com"
                ],
                [
                    "DNS",
                    "shop.intheknow.com"
                ],
                [
                    "DNS",
                    "premium.yahoofinance.com"
                ],
                [
                    "DNS",
                    "o2.welcomescreen.aol.de"
                ],
                [
                    "DNS",
                    "o2.aol.de"
                ],
                [
                    "DNS",
                    "news.aol.jp"
                ],
                [
                    "DNS",
                    "n.sb.welcomescreen.aol.com"
                ],
                [
                    "DNS",
                    "n.main.welcomescreen.aol.com"
                ],
                [
                    "DNS",
                    "fluxible.io.yahoo.net"
                ],
                [
                    "DNS",
                    "engadget.com"
                ],
                [
                    "DNS",
                    "brb.yahoo.net"
                ],
                [
                    "DNS",
                    "autoblog.com"
                ],
                [
                    "DNS",
                    "aolbroadband.welcomescreen.aol.co.uk"
                ],
                [
                    "DNS",
                    "aol.com"
                ],
                [
                    "DNS",
                    "acss.io.yahoo.net"
                ],
                [
                    "DNS",
                    "*.techcrunch.com"
                ],
                [
                    "DNS",
                    "*.strictlyvc.com"
                ],
                [
                    "DNS",
                    "*.shop.intheknow.com"
                ],
                [
                    "DNS",
                    "*.rivals.com"
                ],
                [
                    "DNS",
                    "*.rivals-staging.com"
                ],
                [
                    "DNS",
                    "*.rivals-acceptance.com"
                ],
                [
                    "DNS",
                    "*.n.rivals.com"
                ],
                [
                    "DNS",
                    "*.forums.rivals.com"
                ],
                [
                    "DNS",
                    "*.forums.rivals-staging.com"
                ],
                [
                    "DNS",
                    "*.forums.rivals-acceptance.com"
                ],
                [
                    "DNS",
                    "*.engadget.com"
                ],
                [
                    "DNS",
                    "*.cashay.com"
                ],
                [
                    "DNS",
                    "*.autoblog.com"
                ],
                [
                    "DNS",
                    "*.aol.com"
                ]
            ],
            "OCSP": [
                "http://ocsp.digicert.com"
            ],
            "caIssuers": [
                "http://cacerts.digicert.com/DigiCertSHA2HighAssuranceServerCA.crt"
            ],
            "crlDistributionPoints": [
                "http://crl3.digicert.com/sha2-ha-server-g6.crl",
                "http://crl4.digicert.com/sha2-ha-server-g6.crl"
            ]
        },
        "Middle box - header manipulation test": "No manipulation",
        "Middle box - invalid request line": 0.0,
        "DNS manipulation - repeated query": "No manipulation",
        "DNS manipulation - hijacking detect": "No manipulation",
        "Is domain in G search": "Match",
        "Timestamp": "2024-04-28 17:25:34"
    },
    "canva.com": {
        "Time": 8.32,
        "URL": "canva.com",
        "Resolver Status": "OK",
        "Resolver IP": "31.130.200.2",
        "DNS Status": "OK",
        "DNS IPs": [
            "104.16.102.112",
            "104.16.103.112"
        ],
        "TCP Status": "Established",
        "TCP Remote IP": "104.16.103.112",
        "PING Status": "OK",
        "PING IP": "104.16.103.112",
        "Trace hop IP": "N/A",
        "Redirected Status": "Redirected",
        "Redirected Location": "https://canva.com/",
        "Redirected Location IPs": [
            "OK",
            [
                "104.16.102.112",
                "104.16.103.112"
            ]
        ],
        "HTTP Status": 403,
        "Content Length": 380645,
        "Headers": {
            "Date": "Sun, 28 Apr 2024 21:26:36 GMT",
            "Content-Type": "text/html; charset=UTF-8",
            "Transfer-Encoding": "chunked",
            "Connection": "close",
            "Accept-CH": "Sec-CH-UA-Bitness, Sec-CH-UA-Arch, Sec-CH-UA-Full-Version, Sec-CH-UA-Mobile, Sec-CH-UA-Model, Sec-CH-UA-Platform-Version, Sec-CH-UA-Full-Version-List, Sec-CH-UA-Platform, Sec-CH-UA, UA-Bitness, UA-Arch, UA-Full-Version, UA-Mobile, UA-Model, UA-Platform-Version, UA-Platform, UA",
            "Cross-Origin-Embedder-Policy": "require-corp",
            "Cross-Origin-Opener-Policy": "same-origin",
            "Cross-Origin-Resource-Policy": "same-origin",
            "Origin-Agent-Cluster": "?1",
            "Permissions-Policy": "accelerometer=(),autoplay=(),browsing-topics=(),camera=(),clipboard-read=(),clipboard-write=(),geolocation=(),gyroscope=(),hid=(),interest-cohort=(),magnetometer=(),microphone=(),payment=(),publickey-credentials-get=(),screen-wake-lock=(),serial=(),sync-xhr=(),usb=()",
            "Referrer-Policy": "same-origin",
            "X-Frame-Options": "SAMEORIGIN",
            "cf-mitigated": "challenge",
            "cf-chl-out": "vnTzARmlQ/BDW2C1ujPEzhnkO4YxePAbFPITobsJy0XHGGGUfhKDJoUuTZQWB9YiTOINAwuZOtjjAsA2HfQ1GJUpB0uzhoWSflInV+wbAXpIDTBKCRKk3R3Urnc24vy/NMfVThkXUEoKdVyhmE4M1w==$LPNYC8soq5bFzrUER6cL2g==",
            "Cache-Control": "private, max-age=0, no-store, no-cache, must-revalidate, post-check=0, pre-check=0",
            "Expires": "Thu, 01 Jan 1970 00:00:01 GMT",
            "Set-Cookie": "__cf_bm=vUDLxYjqaT6U83w6culDb80HGTmcIgyZ9bLZvknNHrA-1714339596-1.0.1.1-B2KUB.Js26VJZLrG_K2uEHmkEIuMMw2m2AmsvldMixkWVxBYiMvKZV3N5ja9Lf0G5pBE3njVIzGGoiMYhhPlXQ; path=/; expires=Sun, 28-Apr-24 21:56:36 GMT; domain=.canva.com; HttpOnly; Secure; SameSite=None",
            "Report-To": "{\"endpoints\":[{\"url\":\"https:\\/\\/a.nel.cloudflare.com\\/report\\/v4?s=sr%2BNE%2FKl1sK3HAz4JVSJg2cPQE28l1%2FXPK90v5Qmq9E6Pw7rf4LXtkVbRgoLMMwE8S7rj%2FvaagqhhBCvyxtibs7IETZmDyntasfrOBVW6v4ozz7qXInlT%2Bc9A9uAhtE%3D\"}],\"group\":\"cf-nel\",\"max_age\":604800}",
            "NEL": "{\"success_fraction\":0.01,\"report_to\":\"cf-nel\",\"max_age\":604800}",
            "Vary": "Accept-Encoding",
            "Strict-Transport-Security": "max-age=31536000; includeSubDomains; preload",
            "X-Content-Type-Options": "nosniff",
            "Server": "cloudflare",
            "CF-RAY": "87ba21addf822d81-ARN",
            "Content-Encoding": "gzip"
        },
        "HTML Content": "canva.com_content.html",
        "Cert Status": "OK",
        "Cert Content": {
            "subject": [
                [
                    [
                        "commonName",
                        "canva.com"
                    ]
                ]
            ],
            "issuer": [
                [
                    [
                        "countryName",
                        "US"
                    ]
                ],
                [
                    [
                        "organizationName",
                        "Google Trust Services LLC"
                    ]
                ],
                [
                    [
                        "commonName",
                        "GTS CA 1P5"
                    ]
                ]
            ],
            "version": 3,
            "serialNumber": "1BA73BEDE6DFC3C013E4A5858BBD077C",
            "notBefore": "Mar 12 10:15:01 2024 GMT",
            "notAfter": "Jun 10 10:15:00 2024 GMT",
            "subjectAltName": [
                [
                    "DNS",
                    "canva.com"
                ]
            ],
            "OCSP": [
                "http://ocsp.pki.goog/s/gts1p5/Jny4t9k4ba4"
            ],
            "caIssuers": [
                "http://pki.goog/repo/certs/gts1p5.der"
            ],
            "crlDistributionPoints": [
                "http://crls.pki.goog/gts1p5/PX7fR59yV-s.crl"
            ]
        },
        "Middle box - header manipulation test": "No manipulation",
        "Middle box - invalid request line": 0.0,
        "DNS manipulation - repeated query": "No manipulation",
        "DNS manipulation - hijacking detect": "No manipulation",
        "Is domain in G search": "Match",
        "Timestamp": "2024-04-28 17:26:43"
    },
    "offset.com": {
        "Time": 10.8,
        "URL": "offset.com",
        "Resolver Status": "OK",
        "Resolver IP": "31.130.200.2",
        "DNS Status": "OK",
        "DNS IPs": [
            "76.223.35.209",
            "13.248.178.125"
        ],
        "TCP Status": "Established",
        "TCP Remote IP": "76.223.35.209",
        "PING Status": "OK",
        "PING IP": "76.223.35.209",
        "Trace hop IP": "N/A",
        "Redirected Status": "Redirected",
        "Redirected Location": "https://offset.com:443/",
        "Redirected Location IPs": [
            "OK",
            [
                "76.223.35.209",
                "13.248.178.125"
            ]
        ],
        "HTTP Status": 200,
        "Content Length": 30782,
        "Headers": {
            "Content-Type": "text/html",
            "Transfer-Encoding": "chunked",
            "Connection": "keep-alive",
            "Last-Modified": "Thu, 21 Mar 2024 16:04:14 GMT",
            "x-amz-server-side-encryption": "AES256",
            "Server": "AmazonS3",
            "Content-Encoding": "gzip",
            "Date": "Sun, 21 Apr 2024 10:06:19 GMT",
            "Cache-Control": "public, max-age=31536000",
            "ETag": "W/\"e9bf427654715c36f8de2762d4ab3844\"",
            "Vary": "Accept-Encoding",
            "X-Cache": "Hit from cloudfront",
            "Via": "1.1 4d25e683291a18aef178d8e4f9828b50.cloudfront.net (CloudFront)",
            "X-Amz-Cf-Pop": "FCO50-P3",
            "Alt-Svc": "h3=\":443\"; ma=86400",
            "X-Amz-Cf-Id": "ybEQPG0sM31d4ZC7eBG3DAirWVNuPGjlyQwilpaIX5ce-xncO80BvA==",
            "Age": "645674"
        },
        "HTML Content": "offset.com_content.html",
        "Cert Status": "OK",
        "Cert Content": {
            "subject": [
                [
                    [
                        "commonName",
                        "offset.com"
                    ]
                ]
            ],
            "issuer": [
                [
                    [
                        "countryName",
                        "US"
                    ]
                ],
                [
                    [
                        "organizationName",
                        "Amazon"
                    ]
                ],
                [
                    [
                        "commonName",
                        "Amazon RSA 2048 M02"
                    ]
                ]
            ],
            "version": 3,
            "serialNumber": "0B8ABF748BC4D20153EFD6D1BB4E254B",
            "notBefore": "Jan 25 00:00:00 2024 GMT",
            "notAfter": "Feb 22 23:59:59 2025 GMT",
            "subjectAltName": [
                [
                    "DNS",
                    "offset.com"
                ],
                [
                    "DNS",
                    "*.offset.com"
                ]
            ],
            "OCSP": [
                "http://ocsp.r2m02.amazontrust.com"
            ],
            "caIssuers": [
                "http://crt.r2m02.amazontrust.com/r2m02.cer"
            ],
            "crlDistributionPoints": [
                "http://crl.r2m02.amazontrust.com/r2m02.crl"
            ]
        },
        "Middle box - header manipulation test": "No manipulation",
        "Middle box - invalid request line": 0.0,
        "DNS manipulation - repeated query": "No manipulation",
        "DNS manipulation - hijacking detect": "No manipulation",
        "Is domain in G search": "No match",
        "Timestamp": "2024-04-28 17:27:41"
    },
    "ebay.com": {
        "Time": 26.69,
        "URL": "ebay.com",
        "Resolver Status": "OK",
        "Resolver IP": "31.130.200.2",
        "DNS Status": "OK",
        "DNS IPs": [
            "2.16.6.34",
            "2.16.6.12"
        ],
        "TCP Status": "Established",
        "TCP Remote IP": "2.16.6.34",
        "PING Status": "OK",
        "PING IP": "2.16.6.34",
        "Trace hop IP": "N/A",
        "Redirected Status": "Redirected",
        "Redirected Location": "https://ebay.com/",
        "Redirected Location IPs": [
            "OK",
            [
                "2.16.6.34",
                "2.16.6.12"
            ]
        ],
        "HTTP Status": 503,
        "Content Length": 378,
        "Headers": {
            "Server": "AkamaiGHost",
            "Mime-Version": "1.0",
            "Content-Type": "text/html",
            "Content-Length": "378",
            "Expires": "Sun, 28 Apr 2024 21:28:29 GMT",
            "Date": "Sun, 28 Apr 2024 21:28:29 GMT",
            "Connection": "keep-alive"
        },
        "HTML Content": "ebay.com_content.html",
        "Cert Status": "OK",
        "Cert Content": {
            "subject": [
                [
                    [
                        "countryName",
                        "US"
                    ]
                ],
                [
                    [
                        "stateOrProvinceName",
                        "California"
                    ]
                ],
                [
                    [
                        "organizationName",
                        "eBay, Inc."
                    ]
                ],
                [
                    [
                        "commonName",
                        "ebay.com"
                    ]
                ]
            ],
            "issuer": [
                [
                    [
                        "countryName",
                        "GB"
                    ]
                ],
                [
                    [
                        "stateOrProvinceName",
                        "Greater Manchester"
                    ]
                ],
                [
                    [
                        "localityName",
                        "Salford"
                    ]
                ],
                [
                    [
                        "organizationName",
                        "Sectigo Limited"
                    ]
                ],
                [
                    [
                        "commonName",
                        "Sectigo RSA Organization Validation Secure Server CA"
                    ]
                ]
            ],
            "version": 3,
            "serialNumber": "D5072F2C3B21834D34FBB048F9A5DAC0",
            "notBefore": "Feb 26 00:00:00 2024 GMT",
            "notAfter": "Feb 25 23:59:59 2025 GMT",
            "subjectAltName": [
                [
                    "DNS",
                    "ebay.com"
                ],
                [
                    "DNS",
                    "befr.ebay.be"
                ],
                [
                    "DNS",
                    "benl.ebay.be"
                ],
                [
                    "DNS",
                    "cafr.ebay.ca"
                ],
                [
                    "DNS",
                    "e-bay.it"
                ],
                [
                    "DNS",
                    "ebay.at"
                ],
                [
                    "DNS",
                    "ebay.be"
                ],
                [
                    "DNS",
                    "ebay.ca"
                ],
                [
                    "DNS",
                    "ebay.ch"
                ],
                [
                    "DNS",
                    "ebay.co.uk"
                ],
                [
                    "DNS",
                    "ebay.com.au"
                ],
                [
                    "DNS",
                    "ebay.com.hk"
                ],
                [
                    "DNS",
                    "ebay.com.my"
                ],
                [
                    "DNS",
                    "ebay.com.sg"
                ],
                [
                    "DNS",
                    "ebay.de"
                ],
                [
                    "DNS",
                    "ebay.es"
                ],
                [
                    "DNS",
                    "ebay.fr"
                ],
                [
                    "DNS",
                    "ebay.ie"
                ],
                [
                    "DNS",
                    "ebay.in"
                ],
                [
                    "DNS",
                    "ebay.it"
                ],
                [
                    "DNS",
                    "ebay.nl"
                ],
                [
                    "DNS",
                    "ebay.ph"
                ],
                [
                    "DNS",
                    "ebay.pl"
                ],
                [
                    "DNS",
                    "ebay.us"
                ],
                [
                    "DNS",
                    "ebay.vn"
                ]
            ],
            "OCSP": [
                "http://ocsp.sectigo.com"
            ],
            "caIssuers": [
                "http://crt.sectigo.com/SectigoRSAOrganizationValidationSecureServerCA.crt"
            ],
            "crlDistributionPoints": [
                "http://crl.sectigo.com/SectigoRSAOrganizationValidationSecureServerCA.crl"
            ]
        },
        "Middle box - header manipulation test": "No manipulation",
        "Middle box - invalid request line": 1.0,
        "DNS manipulation - repeated query": "No manipulation",
        "DNS manipulation - hijacking detect": "No manipulation",
        "Is domain in G search": "Match",
        "Timestamp": "2024-04-28 17:28:37"
    },
    "zoom.us": {
        "Time": 9.17,
        "URL": "zoom.us",
        "Resolver Status": "OK",
        "Resolver IP": "31.130.200.2",
        "DNS Status": "OK",
        "DNS IPs": [
            "170.114.52.2"
        ],
        "TCP Status": "Established",
        "TCP Remote IP": "170.114.52.2",
        "PING Status": "OK",
        "PING IP": "170.114.52.2",
        "Trace hop IP": "N/A",
        "Redirected Status": "Redirected",
        "Redirected Location": "https://zoom.us/",
        "Redirected Location IPs": [
            "OK",
            [
                "170.114.52.2"
            ]
        ],
        "HTTP Status": 200,
        "Content Length": 560293,
        "Headers": {
            "Date": "Sun, 28 Apr 2024 21:29:21 GMT",
            "Content-Type": "text/html;charset=utf-8",
            "Transfer-Encoding": "chunked",
            "Connection": "keep-alive",
            "x-zm-trackingid": "v=2.0;clid=aw1;rid=WEB_c07e1cecde155cb79a6015029a947cfc",
            "x-content-type-options": "nosniff",
            "content-security-policy": "upgrade-insecure-requests; default-src https://*.zoom.us https://zoom.us blob: 'self'; img-src https: about: blob: data: 'self'; style-src https: safari-extension: chrome-extension: 'unsafe-inline' data: 'self'; font-src https: safari-extension: chrome-extension: blob: data: 'self'; connect-src * about: blob: data: 'self'; media-src * rtmp: blob: data: 'self'; frame-src https: ms-appx-web: zoommtg: zoomus: wvjbscheme: zoomprc: data: blob: 'self'; object-src 'none'; base-uri 'none';script-src 'self' 'strict-dynamic' 'nonce-CRBJHUNZS-Kn2bCkP6Te-A' blob: https:;",
            "x-frame-options": "SAMEORIGIN",
            "set-cookie": "zm_aid=; Max-Age=0; Expires=Thu, 01 Jan 1970 00:00:10 GMT; Domain=zoom.us; Path=/; Secure; HttpOnly, zm_haid=; Max-Age=0; Expires=Thu, 01 Jan 1970 00:00:10 GMT; Domain=zoom.us; Path=/; Secure; HttpOnly, zm_tmaid=; Max-Age=0; Expires=Thu, 01 Jan 1970 00:00:10 GMT; Domain=zoom.us; Path=/; Secure; HttpOnly, zm_htmaid=; Max-Age=0; Expires=Thu, 01 Jan 1970 00:00:10 GMT; Domain=zoom.us; Path=/; Secure; HttpOnly, _zm_ssid=aw1_c_VsulCP6aQMKanxQjkyVhSA; Domain=zoom.us; Path=/; Secure; HttpOnly, cred=A7F6B9A8FEB7A9845FDB77FDC0FB0585; Path=/; Secure; HttpOnly, _zm_mtk_guid=fd81beca08ed4d9d8a3448063e144d53; Domain=zoom.us; Path=/; Max-Age=63072000; SameSite=None; Secure, _zm_csp_script_nonce=CRBJHUNZS-Kn2bCkP6Te-A; Domain=zoom.us; Path=/; Secure; HttpOnly, _zm_currency=EUR; Max-Age=86400; Expires=Mon, 29 Apr 2024 21:29:21 GMT; Domain=zoom.us; Path=/; Secure, _zm_visitor_guid=fd81beca08ed4d9d8a3448063e144d53; Domain=zoom.us; Path=/; Max-Age=31536000; SameSite=None; Secure",
            "x-zm-zoneid": "VA",
            "content-language": "en-US",
            "strict-transport-security": "max-age=31536000; includeSubDomains",
            "x-xss-protection": "1; mode=block",
            "referrer-policy": "strict-origin-when-cross-origin",
            "Content-Encoding": "gzip",
            "Cache-Control": "private, max-age=0",
            "CF-Cache-Status": "DYNAMIC",
            "Report-To": "{\"endpoints\":[{\"url\":\"https:\\/\\/a.nel.cloudflare.com\\/report\\/v4?s=NqUjK0ZdP%2FC3fV%2BoDawP3KQpKee%2BeJa94uYlQAt3GIMDujMKEhG21exJGdVNHRSbPIt75Ok2pPhkYCy5lCapXgpnDx4NzRcgAR56ZhkQbAFA8GfidSx6ZKU%3D\"}],\"group\":\"cf-nel\",\"max_age\":604800}",
            "NEL": "{\"success_fraction\":0.01,\"report_to\":\"cf-nel\",\"max_age\":604800}",
            "Server": "cloudflare",
            "CF-RAY": "87ba25b66a4d71a9-FRA",
            "alt-svc": "h3=\":443\"; ma=86400"
        },
        "HTML Content": "zoom.us_content.html",
        "Cert Status": "OK",
        "Cert Content": {
            "subject": [
                [
                    [
                        "countryName",
                        "US"
                    ]
                ],
                [
                    [
                        "stateOrProvinceName",
                        "California"
                    ]
                ],
                [
                    [
                        "localityName",
                        "San Jose"
                    ]
                ],
                [
                    [
                        "organizationName",
                        "Zoom Video Communications, Inc."
                    ]
                ],
                [
                    [
                        "commonName",
                        "*.zoom.us"
                    ]
                ]
            ],
            "issuer": [
                [
                    [
                        "countryName",
                        "US"
                    ]
                ],
                [
                    [
                        "organizationName",
                        "DigiCert Inc"
                    ]
                ],
                [
                    [
                        "commonName",
                        "DigiCert Global G2 TLS RSA SHA256 2020 CA1"
                    ]
                ]
            ],
            "version": 3,
            "serialNumber": "06FE306016F7DF44AEF4819F5CD16196",
            "notBefore": "Mar 28 00:00:00 2024 GMT",
            "notAfter": "Apr  5 23:59:59 2025 GMT",
            "subjectAltName": [
                [
                    "DNS",
                    "*.zoom.us"
                ],
                [
                    "DNS",
                    "zoom.us"
                ]
            ],
            "OCSP": [
                "http://ocsp.digicert.com"
            ],
            "caIssuers": [
                "http://cacerts.digicert.com/DigiCertGlobalG2TLSRSASHA2562020CA1-1.crt"
            ],
            "crlDistributionPoints": [
                "http://crl3.digicert.com/DigiCertGlobalG2TLSRSASHA2562020CA1-1.crl",
                "http://crl4.digicert.com/DigiCertGlobalG2TLSRSASHA2562020CA1-1.crl"
            ]
        },
        "Middle box - header manipulation test": "No manipulation",
        "Middle box - invalid request line": 0.0,
        "DNS manipulation - repeated query": "No manipulation",
        "DNS manipulation - hijacking detect": "No manipulation",
        "Is domain in G search": "Match",
        "Timestamp": "2024-04-28 17:29:29"
    },
    "cambridge.org": {
        "Time": 6.33,
        "URL": "cambridge.org",
        "Resolver Status": "OK",
        "Resolver IP": "31.130.200.2",
        "DNS Status": "OK",
        "DNS IPs": [
            "104.17.111.190",
            "104.17.110.190"
        ],
        "TCP Status": "Established",
        "TCP Remote IP": "104.17.111.190",
        "PING Status": "OK",
        "PING IP": "104.17.111.190",
        "Trace hop IP": "N/A",
        "Redirected Status": "Redirected",
        "Redirected Location": "https://www.cambridge.org:443/",
        "Redirected Location IPs": [
            "OK",
            [
                "104.17.111.190",
                "104.17.110.190"
            ]
        ],
        "HTTP Status": 403,
        "Content Length": 15953,
        "Headers": {
            "Date": "Sun, 28 Apr 2024 21:30:14 GMT",
            "Content-Type": "text/html; charset=UTF-8",
            "Transfer-Encoding": "chunked",
            "Connection": "close",
            "Accept-CH": "Sec-CH-UA-Bitness, Sec-CH-UA-Arch, Sec-CH-UA-Full-Version, Sec-CH-UA-Mobile, Sec-CH-UA-Model, Sec-CH-UA-Platform-Version, Sec-CH-UA-Full-Version-List, Sec-CH-UA-Platform, Sec-CH-UA, UA-Bitness, UA-Arch, UA-Full-Version, UA-Mobile, UA-Model, UA-Platform-Version, UA-Platform, UA",
            "Cross-Origin-Embedder-Policy": "require-corp",
            "Cross-Origin-Opener-Policy": "same-origin",
            "Cross-Origin-Resource-Policy": "same-origin",
            "Origin-Agent-Cluster": "?1",
            "Permissions-Policy": "accelerometer=(),autoplay=(),browsing-topics=(),camera=(),clipboard-read=(),clipboard-write=(),geolocation=(),gyroscope=(),hid=(),interest-cohort=(),magnetometer=(),microphone=(),payment=(),publickey-credentials-get=(),screen-wake-lock=(),serial=(),sync-xhr=(),usb=()",
            "Referrer-Policy": "same-origin",
            "X-Frame-Options": "SAMEORIGIN",
            "cf-mitigated": "challenge",
            "cf-chl-out": "fKIOqiX0haFQBpULVjHgv9SCWPobBvWiEtvUSCfJ/eczg86nFOKEvTN9pTXEenmzKTJwqnm2k+qXLr1S2qJwn6nNPgXNpTEA3q43RjTX8gtr3igwx6bU41OMgzdflfF6uMAjJGnKm1siuOtfVWCGAA==$ys1H/v5/qH2J/oQvz8cy4w==",
            "Cache-Control": "private, max-age=0, no-store, no-cache, must-revalidate, post-check=0, pre-check=0",
            "Expires": "Thu, 01 Jan 1970 00:00:01 GMT",
            "Vary": "Accept-Encoding",
            "Server": "cloudflare",
            "CF-RAY": "87ba27018baa9dc1-DME",
            "Content-Encoding": "gzip"
        },
        "HTML Content": "cambridge.org_content.html",
        "Cert Status": "OK",
        "Cert Content": {
            "subject": [
                [
                    [
                        "commonName",
                        "cambridge.org"
                    ]
                ]
            ],
            "issuer": [
                [
                    [
                        "countryName",
                        "US"
                    ]
                ],
                [
                    [
                        "organizationName",
                        "Let's Encrypt"
                    ]
                ],
                [
                    [
                        "commonName",
                        "E1"
                    ]
                ]
            ],
            "version": 3,
            "serialNumber": "04CE5F01B9FC9FE8E24D0D2020C39812B4EF",
            "notBefore": "Apr 14 03:39:28 2024 GMT",
            "notAfter": "Jul 13 03:39:27 2024 GMT",
            "subjectAltName": [
                [
                    "DNS",
                    "*.cambridge.org"
                ],
                [
                    "DNS",
                    "cambridge.org"
                ]
            ],
            "OCSP": [
                "http://e1.o.lencr.org"
            ],
            "caIssuers": [
                "http://e1.i.lencr.org/"
            ]
        },
        "Middle box - header manipulation test": "No manipulation",
        "Middle box - invalid request line": 0.0,
        "DNS manipulation - repeated query": "No manipulation",
        "DNS manipulation - hijacking detect": "No manipulation",
        "Is domain in G search": "Match",
        "Timestamp": "2024-04-28 17:30:19"
    },
    "unsplash.com": {
        "Time": 13.43,
        "URL": "unsplash.com",
        "Resolver Status": "OK",
        "Resolver IP": "31.130.200.2",
        "DNS Status": "OK",
        "DNS IPs": [
            "151.101.193.181",
            "151.101.65.181",
            "151.101.1.181",
            "151.101.129.181"
        ],
        "TCP Status": "Established",
        "TCP Remote IP": "151.101.65.181",
        "PING Status": "OK",
        "PING IP": "151.101.65.181",
        "Trace hop IP": "N/A",
        "Redirected Status": "Redirected",
        "Redirected Location": "https://unsplash.com/",
        "Redirected Location IPs": [
            "OK",
            [
                "151.101.193.181",
                "151.101.65.181",
                "151.101.1.181",
                "151.101.129.181"
            ]
        ],
        "HTTP Status": 200,
        "Content Length": 629711,
        "Headers": {
            "Connection": "keep-alive",
            "Content-Length": "92847",
            "Server": "Cowboy",
            "Report-To": "{\"group\":\"heroku-nel\",\"max_age\":3600,\"endpoints\":[{\"url\":\"https://nel.heroku.com/reports?ts=1714338020&sid=af571f24-03ee-46d1-9f90-ab9030c2c74c&s=IQ1h0LN3VcHhqouX34fOtcRQdygdqbSTaXoEEEz6cns%3D\"}]}",
            "Reporting-Endpoints": "heroku-nel=https://nel.heroku.com/reports?ts=1714338020&sid=af571f24-03ee-46d1-9f90-ab9030c2c74c&s=IQ1h0LN3VcHhqouX34fOtcRQdygdqbSTaXoEEEz6cns%3D",
            "Nel": "{\"report_to\":\"heroku-nel\",\"max_age\":3600,\"success_fraction\":0.005,\"failure_fraction\":0.05,\"response_headers\":[\"Via\"]}",
            "X-Frame-Options": "SAMEORIGIN",
            "Strict-Transport-Security": "max-age=31536000",
            "X-Content-Type-Options": "nosniff",
            "X-Xss-Protection": "1",
            "Referrer-Policy": "origin-when-cross-origin",
            "Link": "<https://images.unsplash.com>; rel=\"preconnect\", <https://plus.unsplash.com>; rel=\"preconnect\"",
            "Content-Type": "text/html; charset=utf-8",
            "Content-Encoding": "gzip",
            "Via": "1.1 vegur, 1.1 varnish, 1.1 varnish",
            "Accept-Ranges": "bytes",
            "Age": "1835",
            "Date": "Sun, 28 Apr 2024 21:30:55 GMT",
            "X-Served-By": "cache-iad-kcgs7200085-IAD, cache-fra-eddf8230021-FRA",
            "X-Cache": "HIT, HIT",
            "X-Cache-Hits": "14, 0",
            "Vary": "x-locale, x-xp-semantic-search, x-xp-enable-illustrations, x-xp-better-load-more, x-logged-in, Accept-Encoding, client-geo-region",
            "Set-Cookie": "require_cookie_consent=false; Expires=Mon, 28 Apr 2025 21:30:55 GMT; path=/;, xp-semantic-search=experiment; expires=Mon, 28 Apr 2025 21:30:55 GMT; path=/;, xp-better-load-more=dark-button; expires=Mon, 28 Apr 2025 21:30:55 GMT; path=/;"
        },
        "HTML Content": "unsplash.com_content.html",
        "Cert Status": "OK",
        "Cert Content": {
            "subject": [
                [
                    [
                        "commonName",
                        "unsplash.com"
                    ]
                ]
            ],
            "issuer": [
                [
                    [
                        "countryName",
                        "BE"
                    ]
                ],
                [
                    [
                        "organizationName",
                        "GlobalSign nv-sa"
                    ]
                ],
                [
                    [
                        "commonName",
                        "GlobalSign Atlas R3 DV TLS CA 2024 Q1"
                    ]
                ]
            ],
            "version": 3,
            "serialNumber": "01860725ECAC8163EB56BEB20D20F933",
            "notBefore": "Apr  3 17:50:18 2024 GMT",
            "notAfter": "May  5 17:50:17 2025 GMT",
            "subjectAltName": [
                [
                    "DNS",
                    "unsplash.com"
                ]
            ],
            "OCSP": [
                "http://ocsp.globalsign.com/ca/gsatlasr3dvtlsca2024q1"
            ],
            "caIssuers": [
                "http://secure.globalsign.com/cacert/gsatlasr3dvtlsca2024q1.crt"
            ],
            "crlDistributionPoints": [
                "http://crl.globalsign.com/ca/gsatlasr3dvtlsca2024q1.crl"
            ]
        },
        "Middle box - header manipulation test": "No manipulation",
        "Middle box - invalid request line": 1.0,
        "DNS manipulation - repeated query": "No manipulation",
        "DNS manipulation - hijacking detect": "No manipulation",
        "Is domain in G search": "Match",
        "Timestamp": "2024-04-28 17:31:03"
    },
    "playstation.com": {
        "Time": 33.02,
        "URL": "playstation.com",
        "Resolver Status": "OK",
        "Resolver IP": "31.130.200.2",
        "DNS Status": "OK",
        "DNS IPs": [
            "54.183.3.8",
            "52.52.207.139"
        ],
        "TCP Status": "Established",
        "TCP Remote IP": "54.183.3.8",
        "PING Status": "Fail",
        "PING IP": "N/A",
        "Trace hop IP": [
            [
                "31.130.202.129",
                0.02644491195678711
            ],
            [
                "212.98.161.17",
                0.017975807189941406
            ],
            [
                "185.11.76.45",
                0.012780904769897461
            ],
            [
                "185.11.76.26",
                0.009224176406860352
            ],
            [
                "223.119.65.185",
                0.025458335876464844
            ],
            [
                "87.245.234.167",
                0.16567134857177734
            ],
            [
                "99.83.65.34",
                0.16656947135925293
            ],
            [
                "223.120.14.134",
                0.10341644287109375
            ],
            [
                "52.95.54.234",
                0.1598055362701416
            ],
            [
                "223.120.6.218",
                0.16295337677001953
            ],
            [
                "99.83.117.125",
                0.158860445022583
            ]
        ],
        "Redirected Status": "Redirected",
        "Redirected Location": "https://playstation.com:443/",
        "Redirected Location IPs": [
            "OK",
            [
                "54.183.3.8",
                "52.52.207.139"
            ]
        ],
        "HTTP Status": 200,
        "Content Length": 162784,
        "Headers": {
            "Accept-Ranges": "bytes",
            "Content-Encoding": "gzip",
            "Content-Type": "text/html;charset=utf-8",
            "ETag": "W/\"27be0-616c964dbe748-gzip\"",
            "Last-Modified": "Tue, 23 Apr 2024 20:28:16 GMT",
            "Server": "Apache",
            "Strict-Transport-Security": "max-age=63072000; includeSubdomains; preload;",
            "X-Content-Type-Options": "nosniff",
            "X-Dispatcher": "dispatcher7uswest1",
            "X-Frame-Options": "SAMEORIGIN",
            "X-Vhost": "publish",
            "Content-Length": "37377",
            "Expires": "Sun, 28 Apr 2024 21:32:35 GMT",
            "Cache-Control": "max-age=0, no-cache, no-store",
            "Pragma": "no-cache",
            "Date": "Sun, 28 Apr 2024 21:32:35 GMT",
            "Connection": "keep-alive",
            "Vary": "Accept-Encoding"
        },
        "HTML Content": "playstation.com_content.html",
        "Cert Status": "OK",
        "Cert Content": {
            "subject": [
                [
                    [
                        "countryName",
                        "US"
                    ]
                ],
                [
                    [
                        "stateOrProvinceName",
                        "California"
                    ]
                ],
                [
                    [
                        "localityName",
                        "San Mateo"
                    ]
                ],
                [
                    [
                        "organizationName",
                        "Sony Interactive Entertainment LLC"
                    ]
                ],
                [
                    [
                        "commonName",
                        "www.playstation.com"
                    ]
                ]
            ],
            "issuer": [
                [
                    [
                        "countryName",
                        "US"
                    ]
                ],
                [
                    [
                        "organizationName",
                        "DigiCert Inc"
                    ]
                ],
                [
                    [
                        "commonName",
                        "DigiCert Global G2 TLS RSA SHA256 2020 CA1"
                    ]
                ]
            ],
            "version": 3,
            "serialNumber": "0F38CF53E92651D73901E69C6D53DE62",
            "notBefore": "Jun 13 00:00:00 2023 GMT",
            "notAfter": "Jun 12 23:59:59 2024 GMT",
            "subjectAltName": [
                [
                    "DNS",
                    "www.playstation.com"
                ],
                [
                    "DNS",
                    "playstation.com"
                ],
                [
                    "DNS",
                    "www.us.playstation.com"
                ],
                [
                    "DNS",
                    "us.playstation.com"
                ]
            ],
            "OCSP": [
                "http://ocsp.digicert.com"
            ],
            "caIssuers": [
                "http://cacerts.digicert.com/DigiCertGlobalG2TLSRSASHA2562020CA1-1.crt"
            ],
            "crlDistributionPoints": [
                "http://crl3.digicert.com/DigiCertGlobalG2TLSRSASHA2562020CA1-1.crl",
                "http://crl4.digicert.com/DigiCertGlobalG2TLSRSASHA2562020CA1-1.crl"
            ]
        },
        "Middle box - header manipulation test": "No manipulation",
        "Middle box - invalid request line": 1.0,
        "DNS manipulation - repeated query": "No manipulation",
        "DNS manipulation - hijacking detect": "No manipulation",
        "Is domain in G search": "Match",
        "Timestamp": "2024-04-28 17:32:45"
    },
    "people.com": {
        "Time": 52.38,
        "URL": "people.com",
        "Resolver Status": "OK",
        "Resolver IP": "31.130.200.2",
        "DNS Status": "OK",
        "DNS IPs": [
            "151.101.194.137",
            "151.101.2.137",
            "151.101.66.137",
            "151.101.130.137"
        ],
        "TCP Status": "Established",
        "TCP Remote IP": "151.101.194.137",
        "PING Status": "OK",
        "PING IP": "151.101.194.137",
        "Trace hop IP": "N/A",
        "Redirected Status": "Redirected",
        "Redirected Location": "https://people.com/",
        "Redirected Location IPs": [
            "OK",
            [
                "151.101.2.137",
                "151.101.66.137",
                "151.101.130.137",
                "151.101.194.137"
            ]
        ],
        "HTTP Status": 200,
        "Content Length": 321014,
        "Headers": {
            "Connection": "keep-alive",
            "x-content-security-policy": "frame-ancestors 'self' *.specless.io *.specless.tech http://*.seo.aws.about.com https://*.seo.aws.about.com http://*.dotdash.com https://*.dotdash.com *.people.com",
            "content-security-policy": "frame-ancestors 'self' *.specless.io *.specless.tech http://*.seo.aws.about.com https://*.seo.aws.about.com http://*.dotdash.com https://*.dotdash.com *.people.com",
            "referrer-policy": "no-referrer-when-downgrade",
            "strict-transport-security": "max-age=15552000",
            "x-abt-application-version": "2.20.0",
            "set-cookie": "TMog=n502eba0d8b974d3d96597db17d86411b21; Path=/; Domain=.people.com; Expires=Sat, 17-May-2092 00:47:19 GMT; Max-Age=2147483647, globalTI_SID=ff046ce5-20c2-47df-80fe-d5127b950a39; Path=/; Domain=.people.com; Expires=Tue, 28-Apr-2026 21:33:12 GMT; Max-Age=63072000, Mint=n502eba0d8b974d3d96597db17d86411b21; Path=/; Domain=.people.com; Expires=Sun, 28-Apr-2024 22:03:12 GMT; Max-Age=1800, pc=1; Path=/; Domain=.people.com; Expires=Sun, 28-Apr-2024 22:03:12 GMT; Max-Age=1800",
            "link": "<//people.com/static/2.20.0/cache/eNqlV1GaoyAMvtDyeYh93UugRGWLxCXYTuf0GxCrtgxDdx9akpA_JCFAbMhLr7tmktYbaDqiJkjgR_M6oSc5gJiN7GBEo8A9lMLsJLXdBTjNaMF6aqRjAVtIo-jQep5oRpwg_pVAM-DMmMTuTqFaDNAR4aQ24qoVYPQmUiX9VlIKtxNSUdYJFX8vqdg1bloNwOMIehj9z1HaAX5p4vjAZYUFW4PBVhpGSRXB8pTgSr1Xs1Ze9cBzaJvFa6P9XbDoSBfAPbqJMwTSdaMIzJEu4CYgCrXSShsycWbrnF0Di77uZB20X4yhzgHYCD-zdSYIOy1NhMcaebC5HcnjMpivC8ii173uopEta2HhjPw_rJH2IFgJxFEjF9JmKY_4ztCXxd0jevZlHQrFndcrb3rUXTf8Qb4FNdpe6MTUwRV6JWkUi9VXcJS2PystGFRcLDikobQw3MiADz4myIukkNh_RIeb0MRT2KJ0qupe7Q186DZc3kX9g9kIyy7zkoXtfQiI58fhoEbQhS2i-M7MfAXx9i5OzEh-p94FepwFeXQaSgXSxYDKUTx0hOhB-sWBqnNmdvwWu7toDXaXM1dYLr7fMWWD7nMLRQP0CPAuvBzO3DfB8LHhBD2o3Bphslr5NXJ_w7QLiaiDkbYDl2KM48QU0jCh1Rc-FiEJB7qAOBrme1c9LbyK6hzeuqWYoyNTB-eJmB0xL5-fhq_SZ0Fl2rzkmJ2Mwe106TzTn0W61FlFsm4lwz0ne9cDqCNdB-60C-lZT8ORqYOPs_Aj9wdrYZ24agNJKLwOx-JZUGdmkoSW6zON71f2dotkhZXmktupvTyzFa1H7LvDN8I99Ry_b4mrWz_2zOtG7GRtJj5W4Ea88zWSjgVvGz9YxjzzdR60IBe_3cpHpvKJ4U5he1lOTCXc4SRCd85IOnN_Ad8qWvw.min.css>; rel=preload; as=style; nopush, <//people.com/static/fonts/limerick_serial-regular-webfont.woff2>; rel=preload; as=font; type=\"font/woff2\"; crossorigin; nopush, <//people.com/static/fonts/limerick_serial-bold-webfont.woff2>; rel=preload; as=font; type=\"font/woff2\"; crossorigin; nopush, <//www.googletagmanager.com/gtm.js?id=GTM-P3X3VT7>; rel=preload; as=script; nopush, <//people.com/static/fonts/limerick_serial-italic-webfont.woff2>; rel=preload; as=font; type=\"font/woff2\"; crossorigin; nopush, <//people.com/static/fonts/limerick_serial-bolditalic-webfont.woff2>; rel=preload; as=font; type=\"font/woff2\"; crossorigin; nopush, <//www.googletagmanager.com/gtag/js?id=G-31EK5CQB08&l=dataLayer&cx=c>; rel=preload; as=script; nopush, <//securepubads.g.doubleclick.net/tag/js/gpt.js>; rel=preload; as=script; nopush, <//people.com/static/2.20.0/cache/eNqFkmFuhCAQhS9UyhnapOnfpvECCCPOioxlBhv39EXTdHXD2kQM-j5mns_RLEbQ6tFECaAtjRNFiMI6mIWy6AuXS9ke7PCkj_Blha4L4xUKQbFDf4_8PgVs-YhjFEgMVpBirS4ZB64iWKIBgStKFgwoda2L6kx2NJ7qM0RHSUufSMqrCjGWjWoTmGGi8mm3IkWbgKYAjxvsMrecuu1WaTHllnN7E8jlAFuqn83ruh5JkowdyuZthr2znXmztFA7_f7RrKsm5YhfGRQHErX-0RojJnkQjF6x6SAgS41iq4zjmpKgOM7QrP5LlT9kF1g5uZJ-klpixoOaEb5PEvcybmMV0A5K7jsdzHQJuDdtgBfH_805P-c4A4a-jCv_AKxrRsA.min.js>; rel=preload; as=script; nopush; group=top, <//people.com/static/2.20.0/cache/eNqNVG1y4yAMvdBqPT3D_t1LyCCwEgEp4KTu6Qs4ad00oZ7xGEm8J-vTQ8qYWQ0quFPw5HMaLqwtlVPNKQcHSlgdIUdUR_b2sfXPcHXj0GehmyY8puFQnteZ4nIPKhdzZuHMlGCcWTJcOE_wFO2KAGf0LIKQVAwi96hNGuwzRY8yaDIUK78JkXSHpFI07fUkig2U3lb__E4g7I8t0x_GjgM0pmSPeUVCpEvkvEZaUI6iomeYL69Bz0Lt07fCCL4vgL0kNVsOE2gSXEjfqR3ebTAmYjvlfxN6S_85ZfIl6kfGji8rYSy9mQh1I9fjlynCl5cFNKME23Hs8cy23AV_na4Fimkrd8gmRJeGRBjVBFXZyh2eo5TQEozoay2-q91O1GyuR2vxvszWerXEvsR9VDOLlN0h8o3-Xd3RfB8yG1bN2S3fw0Pz3rwfDXPdbbzg8uNu42TE1H4LRuiNR6H-0LMrHalwy-YTtrlPpGrsZbqDo1PFFkxc_3BpK-8jS9nZlMFQWbCNDBJQgwuRdpT6zJoCnOpathofLlfll0WR9He0ifIHyh8-uQ.min.js>; rel=preload; as=script; nopush; group=bottom",
            "expires": "Thu, 01 Jan 1970 00:00:00 GMT",
            "content-encoding": "gzip",
            "content-type": "text/html;charset=utf-8",
            "x-content-type-options": "nosniff",
            "Accept-Ranges": "bytes",
            "Via": "1.1 varnish, 1.1 varnish",
            "NEL": "{\"report_to\":\"network-errors\",\"max_age\":2592000,\"success_fraction\":0,\"failure_fraction\":1.0, \"include_subdomains\": true}",
            "Report-To": "{\"group\":\"network-errors\",\"max_age\":2592000,\"endpoints\":[{\"url\":\"https://r.3gl.net/hawklogserver/7815/re.p\"}]}",
            "Date": "Sun, 28 Apr 2024 21:33:12 GMT",
            "X-Served-By": "cache-iad-kjyo7100108-IAD, cache-iad-kjyo7100168-IAD, cache-ams21047-AMS",
            "X-Cache": "MISS, MISS",
            "X-Cache-Hits": "0, 0",
            "X-Timer": "S1714339992.406121,VS0,VE312",
            "transfer-encoding": "chunked"
        },
        "HTML Content": "people.com_content.html",
        "Cert Status": "OK",
        "Cert Content": {
            "subject": [
                [
                    [
                        "commonName",
                        "people.com"
                    ]
                ]
            ],
            "issuer": [
                [
                    [
                        "countryName",
                        "US"
                    ]
                ],
                [
                    [
                        "organizationName",
                        "Let's Encrypt"
                    ]
                ],
                [
                    [
                        "commonName",
                        "R3"
                    ]
                ]
            ],
            "version": 3,
            "serialNumber": "0373F0C470297A05B2CBC102C5360BD25871",
            "notBefore": "Apr 10 08:02:10 2024 GMT",
            "notAfter": "Jul  9 08:02:09 2024 GMT",
            "subjectAltName": [
                [
                    "DNS",
                    "*.people.com"
                ],
                [
                    "DNS",
                    "people.com"
                ]
            ],
            "OCSP": [
                "http://r3.o.lencr.org"
            ],
            "caIssuers": [
                "http://r3.i.lencr.org/"
            ]
        },
        "Middle box - header manipulation test": "No manipulation",
        "Middle box - invalid request line": 0.0,
        "DNS manipulation - repeated query": "No manipulation",
        "DNS manipulation - hijacking detect": "No manipulation",
        "Is domain in G search": "Match",
        "Timestamp": "2024-04-28 17:34:03"
    },
    "springer.com": {
        "Time": 7.09,
        "URL": "springer.com",
        "Resolver Status": "RESOLVER ERROR",
        "Resolver IP": "N/A",
        "DNS Status": "OK",
        "DNS IPs": [
            "151.101.84.95"
        ],
        "TCP Status": "Established",
        "TCP Remote IP": "151.101.84.95",
        "PING Status": "OK",
        "PING IP": "151.101.84.95",
        "Trace hop IP": "N/A",
        "Redirected Status": "Redirected",
        "Redirected Location": "http://www.springer.com/",
        "Redirected Location IPs": [
            "OK",
            [
                "151.101.36.95"
            ]
        ],
        "HTTP Status": 200,
        "Content Length": 38552,
        "Headers": {
            "Connection": "keep-alive",
            "Age": "0",
            "Cache-Control": "private,must-revalidate,max-age=0,no-store",
            "Content-Encoding": "gzip",
            "Content-Type": "text/html; charset=utf-8",
            "Server": "Oscar Platform 0.1290.0",
            "Strict-Transport-Security": "max-age=31536000;preload",
            "X-Vcap-Request-Id": "2df38c9a-b781-45e2-58e9-3d7d8d436a33",
            "Via": "1.1 google, 1.1 varnish",
            "X-Cdn-Origin": "SNPaaS",
            "Accept-Ranges": "bytes",
            "Date": "Sun, 28 Apr 2024 21:34:47 GMT",
            "X-Served-By": "cache-f17b3079-internal, cache-ams21080-AMS",
            "X-Cache": "MISS, MISS",
            "X-Cache-Hits": "0",
            "X-Timer": "S1714340087.010963,VS0,VE103",
            "Vary": "Accept-Encoding",
            "alt-svc": "h3=\":443\";ma=86400,h3-29=\":443\";ma=86400,h3-27=\":443\";ma=86400",
            "transfer-encoding": "chunked"
        },
        "HTML Content": "springer.com_content.html",
        "Cert Status": "OK",
        "Cert Content": {
            "subject": [
                [
                    [
                        "commonName",
                        "springer.com"
                    ]
                ]
            ],
            "issuer": [
                [
                    [
                        "countryName",
                        "US"
                    ]
                ],
                [
                    [
                        "organizationName",
                        "Let's Encrypt"
                    ]
                ],
                [
                    [
                        "commonName",
                        "R3"
                    ]
                ]
            ],
            "version": 3,
            "serialNumber": "03B433B5D7A331DAB215AB992A154F852B8B",
            "notBefore": "Mar  8 09:51:22 2024 GMT",
            "notAfter": "Jun  6 09:51:21 2024 GMT",
            "subjectAltName": [
                [
                    "DNS",
                    "springer.com"
                ]
            ],
            "OCSP": [
                "http://r3.o.lencr.org"
            ],
            "caIssuers": [
                "http://r3.i.lencr.org/"
            ]
        },
        "Middle box - header manipulation test": "No manipulation",
        "Middle box - invalid request line": 0.0,
        "DNS manipulation - repeated query": "No manipulation",
        "DNS manipulation - hijacking detect": "No manipulation",
        "Is domain in G search": "Match",
        "Timestamp": "2024-04-28 17:34:52"
    }
}